odoo/addons/mrp_order_report_stock_location/README.rst
odoo/addons/mrp_order_report_stock_location/__init__.py
odoo/addons/mrp_order_report_stock_location/__manifest__.py
odoo/addons/mrp_order_report_stock_location/static/description/icon.png
odoo/addons/mrp_order_report_stock_location/views/mrp_order_report_stock_location.xml
odoo11_addon_mrp_order_report_stock_location-11.0.1.0.0.dist-info/DESCRIPTION.rst
odoo11_addon_mrp_order_report_stock_location-11.0.1.0.0.dist-info/METADATA
odoo11_addon_mrp_order_report_stock_location-11.0.1.0.0.dist-info/RECORD
odoo11_addon_mrp_order_report_stock_location-11.0.1.0.0.dist-info/WHEEL
odoo11_addon_mrp_order_report_stock_location-11.0.1.0.0.dist-info/metadata.json
odoo11_addon_mrp_order_report_stock_location-11.0.1.0.0.dist-info/top_level.txt
